Workbook

Sheet 假设
A1: 项目 | B1: 值
A2: 税率 | B2: 0.06
A3: 折扣率 | B3: 0.05
A4: 汇率 | B4: 7.1
A5: 单价基准（元） | B5: 1000

Sheet 明细
A1: 月份 | B1: 数量 | C1: 单价 | D1: 金额 | E1: 税额 | F1: 小计 | G1: 毛利率(示例)
A2: 1月 | B2: 120 | C2: 15.5 | D2: =B2*C2 -> 1860 | E2: =D2*假设!$B$3 -> 93 | F2: =D2+E2 -> 1953
A3: 2月 | B3: 135 | C3: 16 | D3: =B3*C3 -> 2160 | E3: =D3*假设!$B$3 -> 108 | F3: =D3+E3 -> 2268
A4: 3月 | B4: 110 | C4: 15.8 | D4: =B4*C4 -> 1738 | E4: =D4*假设!$B$3 -> 86.9 | F4: =D4+E4 -> 1824.9
A5: 4月 | B5: 128 | C5: 16.2 | D5: =B5*C5 -> 2073.6 | E5: =D5*假设!$B$3 -> 103.68 | F5: =D5+E5 -> 2177.28 | G5: =D5/(C5-C5) -> #DIV/0!
A6: 5月 | B6: 140 | C6: 15.9 | D6: =B6*C6 -> 2226 | E6: =D6*假设!$B$3 -> 111.3 | F6: =D6+E6 -> 2337.3
A7: 6月 | B7: 150 | C7: 16.5 | D7: =B7*C7 -> 2475 | E7: =D7*假设!$B$3 -> 123.75 | F7: =D7+E6 -> 2586.3
A8: 7月 | B8: 132 | C8: 16.8 | D8: =B8*C8 -> 2217.6 | E8: =D8*假设!$B$3 -> 110.88 | F8: =D8+E8 -> 2328.48
A9: 8月 | B9: 145 | C9: 16.3 | D9: 2300 | E9: =D9*假设!$B$3 -> 115 | F9: =D9+E9 -> 2415
A10: 9月 | B10: 138 | C10: 16 | D10: =B10*C10 -> 2208 | E10: =D10*假设!$B$3 -> 110.4 | F10: =D10+E10 -> 2318.4
A11: 10月 | B11: 160 | C11: 17 | D11: =B11*C11 -> 2720 | E11: =D11*假设!$B$3 -> 136 | F11: =D11+E11 -> 2856
A12: 11月 | B12: 155 | C12: 16.9 | D12: 见附注 | E12: =D12*假设!$B$3 -> 0 | F12: =D12+E12 -> 0
A13: 12月 | B13: 148 | C13: 17.2 | D13: =B13*C13 -> 2545.6 | E13: =D13*假设!$B$3 -> 127.28 | F13: =D13+E13 -> 2672.88
A14: 合计 | B14: =SUM(B2:B12) -> 1423 | D14: =SUM(D2:D13) -> 24523.8 | E14: =SUM(E2:E13) -> 1226.19 | F14: =SUM(F2:F13) -> 25737.54

Sheet 汇总
A1: 指标 | B1: 数值
A2: 总数量 | B2: =明细!B14 -> 1423
A3: 总小计（关键指标） | B3: =明细!F14 -> 25737.54
A4: 平均单价 | B4: =明细!D14/明细!B14 -> 17.23
A5: 税负 | B5: =明细!E14/明细!D14 -> 0.05
A6: 参考（勿删） | B6: =旧汇总!C4 -> 0

Sheet 说明
A1: 季度成本预算模型 — 使用说明
A2: 序号 | B2: 说明
A3: 1 | B3: 税率与折扣率见"假设"表，改动后需要重新核对"汇总"表。
A4: 参考区间 | C4: 1,200
A5: 2 | B5: 年度基准单价区间为 1,200–1,500 元/件（仅供参考，不参与计算）。
